MANIFEST.in
README.md
requirements.txt
setup.py
metabolic_niche_space/__init__.py
metabolic_niche_space/manifold.py
metabolic_niche_space/neighbors.py
metabolic_niche_space.egg-info/PKG-INFO
metabolic_niche_space.egg-info/SOURCES.txt
metabolic_niche_space.egg-info/dependency_links.txt
metabolic_niche_space.egg-info/requires.txt
metabolic_niche_space.egg-info/top_level.txt